{ "women": {
    "powerless": -16.272727272727273,
    "powerful": 2.090909090909091,
    "low status": -15.181818181818182,
    "high status": 0.0909090909090909,
    "dominated": -16.90909090909091,
    "dominant": 0.0909090909090909,
    "poor": -9.0,
    "wealthy": 1.0,
    "unconfident": -8.545454545454545,
    "confident": 1.181818181818182,
    "unassertive": -9.909090909090908,
    "competitive": 0.6363636363636364,
    "traditional": -13.363636363636363,
    "modern": 1.4545454545454546,
    "religious": -0.5454545454545454,
    "non religious": 11.909090909090908,
    "conservative": -11.090909090909092,
    "liberal": 0.8181818181818182,
    "untrustworthy": -0.3636363636363636,
    "trustworthy": 9.454545454545457,
    "dishonest": -1.3636363636363635,
    "sincere": 10.454545454545457,
    "cold": -1.9090909090909087,
    "warm": 9.545454545454543,
    "threatening": -1.181818181818182,
    "benevolent": 10.636363636363637,
    "repellent": -2.727272727272727,
    "likable": 7.272727272727272,
    "egoistic": -6.454545454545454,
    "altruistic": 7.909090909090909,
    "irrational": -9.727272727272728,
    "rational": 1.181818181818182
  },
  "immigrants": {
    "powerless": -11.428571428571429,
    "powerful": 7.0,
    "low status": -11.714285714285714,
    "high status": 4.857142857142857,
    "dominated": -10.857142857142858,
    "dominant": 7.571428571428571,
    "poor": -2.7142857142857144,
    "wealthy": 13.571428571428571,
    "unconfident": -6.0,
    "confident": 5.714285714285714,
    "unassertive": -5.571428571428571,
    "competitive": 6.0,
    "traditional": -6.428571428571429,
    "modern": 9.857142857142858,
    "religious": -7.428571428571429,
    "non religious": 1.8571428571428568,
    "conservative": -3.4285714285714284,
    "liberal": 15.285714285714286,
    "untrustworthy": -5.857142857142857,
    "trustworthy": 8.571428571428571,
    "dishonest": -2.142857142857143,
    "sincere": 10.428571428571429,
    "cold": -7.571428571428571,
    "warm": 5.571428571428571,
    "threatening": -8.142857142857142,
    "benevolent": 12.428571428571429,
    "repellent": -9.857142857142858,
    "likable": 4.571428571428571,
    "egoistic": -13.428571428571429,
    "altruistic": 2.571428571428572,
    "irrational": -9.142857142857142,
    "rational": 12.857142857142858
  },
  "civil servants": {
    "powerless": 0.0,
    "powerful": 32.875,
    "low status": 0.0,
    "high status": 28.25,
    "dominated": 0.0,
    "dominant": 27.5,
    "poor": 0.0,
    "wealthy": 22.75,
    "unconfident": 0.0,
    "confident": 20.25,
    "unassertive": 0.0,
    "competitive": 23.5,
    "traditional": -19.875,
    "modern": 9.125,
    "religious": 0.0,
    "non religious": 34.0,
    "conservative": -12.125,
    "liberal": 8.5,
    "untrustworthy": -6.75,
    "trustworthy": 7.0,
    "dishonest": -5.0,
    "sincere": 5.125,
    "cold": -5.875,
    "warm": 4.625,
    "threatening": -2.375,
    "benevolent": 5.125,
    "repellent": -8.25,
    "likable": 1.875,
    "egoistic": -9.0,
    "altruistic": 4.5,
    "irrational": -2.375,
    "rational": 7.5
  },
  "disabled people": {
    "powerless": -34.833333333333336,
    "powerful": 0.0,
    "low status": -22.5,
    "high status": 0.0,
    "dominated": -33.5,
    "dominant": 0.0,
    "poor": -19.33333333333333,
    "wealthy": 0.0,
    "unconfident": -24.666666666666668,
    "confident": 0.0,
    "unassertive": -15.666666666666666,
    "competitive": 0.0,
    "traditional": -6.5,
    "modern": 0.6666666666666666,
    "religious": -8.0,
    "non religious": 2.0,
    "conservative": -8.0,
    "liberal": 2.833333333333333,
    "untrustworthy": -4.5,
    "trustworthy": 3.333333333333333,
    "dishonest": 0.0,
    "sincere": 9.166666666666666,
    "cold": -1.5,
    "warm": 6.666666666666667,
    "threatening": 0.0,
    "benevolent": 11.833333333333334,
    "repellent": -3.6666666666666665,
    "likable": 5.5,
    "egoistic": -1.6666666666666667,
    "altruistic": 0.8333333333333334,
    "irrational": -5.5,
    "rational": 2.0
  },
  "Muscovites": {
    "powerless": 0.0,
    "powerful": 44.0,
    "low status": 0.0,
    "high status": 40.0,
    "dominated": 0.0,
    "dominant": 50.0,
    "poor": 0.0,
    "wealthy": 35.0,
    "unconfident": 0.0,
    "confident": 29.0,
    "unassertive": 0.0,
    "competitive": 40.0,
    "traditional": -21.0,
    "modern": 0.0,
    "religious": -28.0,
    "non religious": 0.0,
    "conservative": -27.0,
    "liberal": 0.0,
    "untrustworthy": -35.0,
    "trustworthy": 0.0,
    "dishonest": -34.0,
    "sincere": 0.0,
    "cold": -20.0,
    "warm": 0.0,
    "threatening": -50.0,
    "benevolent": 0.0,
    "repellent": -11.0,
    "likable": 0.0,
    "egoistic": -38.0,
    "altruistic": 0.0,
    "irrational": -10.0,
    "rational": 0.0
  },
  "Texans": {
    "powerless": 0.0,
    "powerful": 35.0,
    "low status": 0.0,
    "high status": 38.0,
    "dominated": 0.0,
    "dominant": 29.0,
    "poor": 0.0,
    "wealthy": 50.0,
    "unconfident": 0.0,
    "confident": 50.0,
    "unassertive": 0.0,
    "competitive": 15.0,
    "traditional": -50.0,
    "modern": 0.0,
    "religious": -48.0,
    "non religious": 0.0,
    "conservative": -50.0,
    "liberal": 0.0,
    "untrustworthy": 0.0,
    "trustworthy": 44.0,
    "dishonest": -8.0,
    "sincere": 0.0,
    "cold": 0.0,
    "warm": 13.0,
    "threatening": -46.0,
    "benevolent": 0.0,
    "repellent": -43.0,
    "likable": 0.0,
    "egoistic": -50.0,
    "altruistic": 0.0,
    "irrational": 0.0,
    "rational": 17.0
  },
  "Shanghainese people": {
    "powerless": 0.0,
    "powerful": 14.833333333333334,
    "low status": 0.0,
    "high status": 16.333333333333332,
    "dominated": 0.0,
    "dominant": 16.166666666666668,
    "poor": -1.6666666666666667,
    "wealthy": 19.33333333333333,
    "unconfident": 0.0,
    "confident": 22.166666666666668,
    "unassertive": -2.0,
    "competitive": 15.333333333333334,
    "traditional": -0.5,
    "modern": 22.0,
    "religious": -6.0,
    "non religious": 11.833333333333334,
    "conservative": 0.0,
    "liberal": 17.833333333333332,
    "untrustworthy": -3.1666666666666665,
    "trustworthy": 13.0,
    "dishonest": -1.5,
    "sincere": 11.666666666666666,
    "cold": -1.8333333333333333,
    "warm": 10.5,
    "threatening": 0.0,
    "benevolent": 15.5,
    "repellent": 0.0,
    "likable": 13.333333333333334,
    "egoistic": -4.833333333333333,
    "altruistic": 2.1666666666666665,
    "irrational": 0.0,
    "rational": 17.833333333333332
  },
  "housewives": {
    "powerless": -19.75,
    "powerful": 1.625,
    "low status": -20.0,
    "high status": 0.0,
    "dominated": -16.625,
    "dominant": 1.625,
    "poor": -8.625,
    "wealthy": 3.375,
    "unconfident": -12.0,
    "confident": 6.75,
    "unassertive": -6.0,
    "competitive": 6.375,
    "traditional": -24.5,
    "modern": 1.625,
    "religious": -7.75,
    "non religious": 10.875,
    "conservative": -16.875,
    "liberal": 2.125,
    "untrustworthy": -3.75,
    "trustworthy": 9.625,
    "dishonest": -0.125,
    "sincere": 16.375,
    "cold": -0.125,
    "warm": 19.25,
    "threatening": -0.125,
    "benevolent": 20.5,
    "repellent": -2.0,
    "likable": 11.5,
    "egoistic": 0.0,
    "altruistic": 18.375,
    "irrational": -2.5,
    "rational": 6.375
  },
  "single mothers": {
    "powerless": -17.77777777777778,
    "powerful": 12.0,
    "low status": -12.22222222222222,
    "high status": 1.4444444444444444,
    "dominated": -16.555555555555557,
    "dominant": 3.555555555555556,
    "poor": -14.11111111111111,
    "wealthy": 0.0,
    "unconfident": -9.666666666666666,
    "confident": 4.666666666666667,
    "unassertive": -8.0,
    "competitive": 8.333333333333334,
    "traditional": -5.333333333333333,
    "modern": 6.555555555555555,
    "religious": 0.0,
    "non religious": 5.888888888888889,
    "conservative": -2.111111111111111,
    "liberal": 7.444444444444445,
    "untrustworthy": -1.1111111111111112,
    "trustworthy": 18.33333333333333,
    "dishonest": -1.6666666666666667,
    "sincere": 10.333333333333334,
    "cold": 0.0,
    "warm": 16.22222222222222,
    "threatening": 0.0,
    "benevolent": 13.666666666666666,
    "repellent": 0.0,
    "likable": 9.22222222222222,
    "egoistic": -3.7777777777777777,
    "altruistic": 16.11111111111111,
    "irrational": -2.4444444444444446,
    "rational": 4.555555555555555
  },
  "men": {
    "powerless": 0.0,
    "powerful": 23.77777777777778,
    "low status": 0.0,
    "high status": 11.666666666666666,
    "dominated": 0.0,
    "dominant": 18.0,
    "poor": -1.0,
    "wealthy": 10.444444444444445,
    "unconfident": -1.5555555555555556,
    "confident": 13.11111111111111,
    "unassertive": 0.0,
    "competitive": 24.77777777777778,
    "traditional": -14.444444444444445,
    "modern": 0.1111111111111111,
    "religious": -1.0,
    "non religious": 17.555555555555557,
    "conservative": -6.444444444444445,
    "liberal": 2.4444444444444446,
    "untrustworthy": -6.333333333333333,
    "trustworthy": 8.333333333333334,
    "dishonest": -6.444444444444445,
    "sincere": 3.6666666666666665,
    "cold": -7.222222222222222,
    "warm": 3.0,
    "threatening": -2.6666666666666665,
    "benevolent": 3.333333333333333,
    "repellent": -3.0,
    "likable": 3.111111111111111,
    "egoistic": -7.777777777777778,
    "altruistic": 1.6666666666666667,
    "irrational": -1.2222222222222223,
    "rational": 14.555555555555555
  },
  "gay men": {
    "powerless": -21.714285714285715,
    "powerful": 0.0,
    "low status": -20.0,
    "high status": 0.0,
    "dominated": -20.428571428571427,
    "dominant": 0.1428571428571428,
    "poor": 0.0,
    "wealthy": 10.714285714285714,
    "unconfident": -10.142857142857142,
    "confident": 4.285714285714286,
    "unassertive": -6.428571428571429,
    "competitive": 4.857142857142857,
    "traditional": 0.0,
    "modern": 33.142857142857146,
    "religious": 0.0,
    "non religious": 29.142857142857142,
    "conservative": 0.0,
    "liberal": 30.285714285714285,
    "untrustworthy": -8.285714285714286,
    "trustworthy": 3.7142857142857135,
    "dishonest": -8.428571428571429,
    "sincere": 6.714285714285714,
    "cold": -5.428571428571429,
    "warm": 12.0,
    "threatening": -7.142857142857143,
    "benevolent": 9.571428571428571,
    "repellent": -9.285714285714286,
    "likable": 2.571428571428572,
    "egoistic": -6.857142857142857,
    "altruistic": 1.8571428571428568,
    "irrational": -6.428571428571429,
    "rational": 6.285714285714286
  },
  "lesbians": {
    "powerless": -7.571428571428571,
    "powerful": 2.142857142857143,
    "low status": -12.857142857142858,
    "high status": 0.8571428571428571,
    "dominated": -9.285714285714286,
    "dominant": 1.2857142857142858,
    "poor": -2.857142857142857,
    "wealthy": 1.1428571428571428,
    "unconfident": -4.571428571428571,
    "confident": 1.5714285714285714,
    "unassertive": -2.0,
    "competitive": 3.4285714285714284,
    "traditional": 0.0,
    "modern": 25.285714285714285,
    "religious": 0.0,
    "non religious": 16.714285714285715,
    "conservative": -4.0,
    "liberal": 22.428571428571427,
    "untrustworthy": -4.571428571428571,
    "trustworthy": 3.0,
    "dishonest": -8.571428571428571,
    "sincere": 1.1428571428571428,
    "cold": -7.142857142857143,
    "warm": 3.857142857142857,
    "threatening": -7.285714285714286,
    "benevolent": 4.285714285714286,
    "repellent": -12.857142857142858,
    "likable": 1.2857142857142858,
    "egoistic": -14.142857142857142,
    "altruistic": 1.8571428571428568,
    "irrational": -15.571428571428571,
    "rational": 1.8571428571428568
  },
  "software engineers": {
    "powerless": -1.1111111111111112,
    "powerful": 21.55555555555556,
    "low status": 0.0,
    "high status": 20.22222222222222,
    "dominated": -0.5555555555555556,
    "dominant": 12.11111111111111,
    "poor": 0.0,
    "wealthy": 28.0,
    "unconfident": -2.7777777777777777,
    "confident": 19.88888888888889,
    "unassertive": -2.4444444444444446,
    "competitive": 20.11111111111111,
    "traditional": -1.5555555555555556,
    "modern": 21.55555555555556,
    "religious": 0.0,
    "non religious": 20.444444444444443,
    "conservative": -2.2222222222222223,
    "liberal": 19.33333333333333,
    "untrustworthy": 0.0,
    "trustworthy": 20.33333333333333,
    "dishonest": -1.5555555555555556,
    "sincere": 16.666666666666668,
    "cold": -9.22222222222222,
    "warm": 1.8888888888888888,
    "threatening": 0.0,
    "benevolent": 13.11111111111111,
    "repellent": 0.0,
    "likable": 12.555555555555555,
    "egoistic": -6.111111111111111,
    "altruistic": 4.222222222222222,
    "irrational": 0.0,
    "rational": 39.11111111111112
  },
  "wealthy people": {
    "powerless": 0.0,
    "powerful": 38.125,
    "low status": 0.0,
    "high status": 36.25,
    "dominated": 0.0,
    "dominant": 40.375,
    "poor": 0.0,
    "wealthy": 45.25,
    "unconfident": -2.875,
    "confident": 28.375,
    "unassertive": -2.25,
    "competitive": 28.0,
    "traditional": -7.875,
    "modern": 13.875,
    "religious": -3.625,
    "non religious": 21.125,
    "conservative": -7.25,
    "liberal": 8.0,
    "untrustworthy": -16.375,
    "trustworthy": 5.25,
    "dishonest": -18.25,
    "sincere": 4.0,
    "cold": -16.5,
    "warm": 0.125,
    "threatening": -15.625,
    "benevolent": 0.0,
    "repellent": -12.125,
    "likable": 0.375,
    "egoistic": -21.875,
    "altruistic": 2.625,
    "irrational": 0.0,
    "rational": 17.75
  },
  "poor people": {
    "powerless": -43.125,
    "powerful": 0.0,
    "low status": -36.625,
    "high status": 4.25,
    "dominated": -39.0,
    "dominant": 2.75,
    "poor": -50.0,
    "wealthy": 0.0,
    "unconfident": -35.5,
    "confident": 0.375,
    "unassertive": -20.625,
    "competitive": 3.375,
    "traditional": -32.375,
    "modern": 0.0,
    "religious": 0.0,
    "non religious": 21.0,
    "conservative": -26.5,
    "liberal": 0.0,
    "untrustworthy": -19.5,
    "trustworthy": 7.625,
    "dishonest": -13.625,
    "sincere": 11.125,
    "cold": -9.25,
    "warm": 13.75,
    "threatening": -6.25,
    "benevolent": 15.25,
    "repellent": -19.25,
    "likable": 8.125,
    "egoistic": -3.75,
    "altruistic": 9.375,
    "irrational": -13.0,
    "rational": 7.5
  },
  "Asian people": {
    "powerless": -2.333333333333333,
    "powerful": 13.416666666666666,
    "low status": -3.583333333333333,
    "high status": 5.583333333333333,
    "dominated": -2.583333333333333,
    "dominant": 9.416666666666666,
    "poor": -3.1666666666666665,
    "wealthy": 7.083333333333333,
    "unconfident": -6.416666666666667,
    "confident": 2.6666666666666665,
    "unassertive": -7.083333333333333,
    "competitive": 11.583333333333334,
    "traditional": -19.0,
    "modern": 1.6666666666666667,
    "religious": -10.666666666666666,
    "non religious": 6.916666666666667,
    "conservative": -17.583333333333332,
    "liberal": 0.0833333333333333,
    "untrustworthy": -1.0833333333333333,
    "trustworthy": 20.916666666666668,
    "dishonest": -2.9166666666666665,
    "sincere": 15.583333333333334,
    "cold": -8.083333333333334,
    "warm": 10.833333333333334,
    "threatening": 0.0,
    "benevolent": 18.0,
    "repellent": -0.3333333333333333,
    "likable": 15.916666666666666,
    "egoistic": -5.416666666666667,
    "altruistic": 5.0,
    "irrational": -0.6666666666666666,
    "rational": 15.083333333333334
  },
  "Black people": {
    "powerless": -5.625,
    "powerful": 14.125,
    "low status": -13.5,
    "high status": 3.625,
    "dominated": -4.375,
    "dominant": 12.5,
    "poor": -22.75,
    "wealthy": 0.0,
    "unconfident": -5.0,
    "confident": 17.75,
    "unassertive": -3.25,
    "competitive": 19.375,
    "traditional": -6.25,
    "modern": 14.875,
    "religious": -13.5,
    "non religious": 2.125,
    "conservative": -3.25,
    "liberal": 16.375,
    "untrustworthy": -28.5,
    "trustworthy": 0.0,
    "dishonest": -11.625,
    "sincere": 0.375,
    "cold": -7.875,
    "warm": 1.625,
    "threatening": -28.0,
    "benevolent": 0.0,
    "repellent": -20.75,
    "likable": 0.0,
    "egoistic": -16.625,
    "altruistic": 1.25,
    "irrational": -13.25,
    "rational": 4.875
  },
  "Muslim people": {
    "powerless": -13.4,
    "powerful": 1.4,
    "low status": -15.8,
    "high status": 0.0,
    "dominated": -11.0,
    "dominant": 7.8,
    "poor": -15.4,
    "wealthy": 4.2,
    "unconfident": -9.4,
    "confident": 10.0,
    "unassertive": -4.0,
    "competitive": 7.2,
    "traditional": -36.6,
    "modern": 2.0,
    "religious": -47.4,
    "non religious": 0.0,
    "conservative": -32.4,
    "liberal": 0.0,
    "untrustworthy": -11.8,
    "trustworthy": 0.0,
    "dishonest": -10.4,
    "sincere": 1.0,
    "cold": -14.6,
    "warm": 1.0,
    "threatening": -22.6,
    "benevolent": 0.0,
    "repellent": -15.4,
    "likable": 0.0,
    "egoistic": -12.4,
    "altruistic": 0.0,
    "irrational": -13.0,
    "rational": 0.0
  },
  "government officials": {
    "powerless": 0.0,
    "powerful": 45.5,
    "low status": 0.0,
    "high status": 38.16666666666666,
    "dominated": 0.0,
    "dominant": 44.833333333333336,
    "poor": 0.0,
    "wealthy": 39.5,
    "unconfident": 0.0,
    "confident": 40.333333333333336,
    "unassertive": -1.8333333333333333,
    "competitive": 33.833333333333336,
    "traditional": -24.666666666666668,
    "modern": 4.166666666666667,
    "religious": -7.166666666666667,
    "non religious": 31.0,
    "conservative": -24.166666666666668,
    "liberal": 2.833333333333333,
    "untrustworthy": -15.833333333333334,
    "trustworthy": 13.333333333333334,
    "dishonest": -15.5,
    "sincere": 6.666666666666667,
    "cold": -16.166666666666668,
    "warm": 5.5,
    "threatening": -10.0,
    "benevolent": 7.0,
    "repellent": -13.666666666666666,
    "likable": 6.166666666666667,
    "egoistic": -21.0,
    "altruistic": 5.0,
    "irrational": -5.833333333333333,
    "rational": 18.166666666666668
  },
  "feminists": {
    "powerless": 0.0,
    "powerful": 26.0,
    "low status": -2.2,
    "high status": 15.0,
    "dominated": -7.4,
    "dominant": 23.2,
    "poor": -1.0,
    "wealthy": 5.8,
    "unconfident": 0.0,
    "confident": 32.8,
    "unassertive": 0.0,
    "competitive": 35.4,
    "traditional": 0.0,
    "modern": 37.8,
    "religious": 0.0,
    "non religious": 13.2,
    "conservative": 0.0,
    "liberal": 30.8,
    "untrustworthy": -1.0,
    "trustworthy": 16.4,
    "dishonest": -0.4,
    "sincere": 12.2,
    "cold": -0.8,
    "warm": 5.0,
    "threatening": 0.0,
    "benevolent": 5.0,
    "repellent": -4.4,
    "likable": 0.2,
    "egoistic": -2.0,
    "altruistic": 3.8,
    "irrational": -5.8,
    "rational": 0.0
  },
  "veterans": {
    "powerless": -10.0,
    "powerful": 16.0,
    "low status": -5.4,
    "high status": 11.8,
    "dominated": -5.8,
    "dominant": 13.4,
    "poor": -3.2,
    "wealthy": 6.6,
    "unconfident": 0.0,
    "confident": 14.8,
    "unassertive": -4.6,
    "competitive": 15.6,
    "traditional": -26.2,
    "modern": 0.0,
    "religious": -4.2,
    "non religious": 28.6,
    "conservative": -25.6,
    "liberal": 0.0,
    "untrustworthy": 0.0,
    "trustworthy": 22.4,
    "dishonest": 0.0,
    "sincere": 20.4,
    "cold": -6.0,
    "warm": 11.6,
    "threatening": -3.4,
    "benevolent": 8.2,
    "repellent": 0.0,
    "likable": 9.6,
    "egoistic": 0.0,
    "altruistic": 17.6,
    "irrational": -10.0,
    "rational": 13.0
  },
  "Hui people": {
    "powerless": -4.0,
    "powerful": 4.6,
    "low status": -6.2,
    "high status": 3.8,
    "dominated": -4.2,
    "dominant": 3.8,
    "poor": -5.2,
    "wealthy": 3.6,
    "unconfident": -4.2,
    "confident": 0.2,
    "unassertive": -4.2,
    "competitive": 2.8,
    "traditional": -30.4,
    "modern": 0.0,
    "religious": -31.4,
    "non religious": 0.0,
    "conservative": -17.8,
    "liberal": 0.0,
    "untrustworthy": -9.0,
    "trustworthy": 0.0,
    "dishonest": -10.2,
    "sincere": 0.0,
    "cold": -3.0,
    "warm": 2.6,
    "threatening": -11.2,
    "benevolent": 0.0,
    "repellent": -8.4,
    "likable": 0.0,
    "egoistic": -5.8,
    "altruistic": 0.0,
    "irrational": -12.2,
    "rational": 0.0
  },
  "migrant workers": {
    "powerless": -28.714285714285715,
    "powerful": 1.4285714285714286,
    "low status": -32.0,
    "high status": 0.0,
    "dominated": -33.857142857142854,
    "dominant": 0.0,
    "poor": -22.714285714285715,
    "wealthy": 1.4285714285714286,
    "unconfident": -22.285714285714285,
    "confident": 4.0,
    "unassertive": -24.0,
    "competitive": 1.0,
    "traditional": -24.571428571428573,
    "modern": 0.0,
    "religious": -1.7142857142857142,
    "non religious": 8.0,
    "conservative": -18.142857142857142,
    "liberal": 0.0,
    "untrustworthy": -1.7142857142857142,
    "trustworthy": 16.285714285714285,
    "dishonest": 0.0,
    "sincere": 19.142857142857142,
    "cold": -1.0,
    "warm": 19.428571428571427,
    "threatening": -5.857142857142857,
    "benevolent": 16.428571428571427,
    "repellent": -7.0,
    "likable": 7.571428571428571,
    "egoistic": -2.857142857142857,
    "altruistic": 8.571428571428571,
    "irrational": -8.571428571428571,
    "rational": 10.428571428571429
  },
  "Chechentsy": {
    "powerless": 0.0,
    "powerful": 19.5,
    "low status": 0.0,
    "high status": 15.0,
    "dominated": 0.0,
    "dominant": 22.5,
    "poor": -12.5,
    "wealthy": 3.0,
    "unconfident": -3.5,
    "confident": 17.0,
    "unassertive": 0.0,
    "competitive": 35.5,
    "traditional": 0.0,
    "modern": 7.5,
    "religious": -25.0,
    "non religious": 5.5,
    "conservative": -25.0,
    "liberal": 5.5,
    "untrustworthy": -25.0,
    "trustworthy": 4.5,
    "dishonest": -25.0,
    "sincere": 11.0,
    "cold": -25.0,
    "warm": 2.0,
    "threatening": -38.0,
    "benevolent": 0.0,
    "repellent": -29.0,
    "likable": 0.0,
    "egoistic": -28.5,
    "altruistic": 0.0,
    "irrational": -30.0,
    "rational": 0.0
  },
  "VDV soldiers": {
    "powerless": 0.0,
    "powerful": 40.0,
    "low status": 0.0,
    "high status": 38.0,
    "dominated": 0.0,
    "dominant": 50.0,
    "poor": 0.0,
    "wealthy": 35.0,
    "unconfident": 0.0,
    "confident": 36.0,
    "unassertive": 0.0,
    "competitive": 37.0,
    "traditional": -38.0,
    "modern": 0.0,
    "religious": -24.0,
    "non religious": 0.0,
    "conservative": -33.0,
    "liberal": 0.0,
    "untrustworthy": -30.0,
    "trustworthy": 0.0,
    "dishonest": -34.0,
    "sincere": 0.0,
    "cold": -29.0,
    "warm": 0.0,
    "threatening": -32.0,
    "benevolent": 0.0,
    "repellent": -3.0,
    "likable": 0.0,
    "egoistic": -11.0,
    "altruistic": 0.0,
    "irrational": 0.0,
    "rational": 0.0
  },
  "Mormon people": {
    "powerless": 0.0,
    "powerful": 23.0,
    "low status": -21.0,
    "high status": 0.0,
    "dominated": -21.0,
    "dominant": 0.0,
    "poor": 0.0,
    "wealthy": 10.0,
    "unconfident": 0.0,
    "confident": 11.0,
    "unassertive": -50.0,
    "competitive": 0.0,
    "traditional": -50.0,
    "modern": 0.0,
    "religious": -50.0,
    "non religious": 0.0,
    "conservative": -50.0,
    "liberal": 0.0,
    "untrustworthy": -10.0,
    "trustworthy": 0.0,
    "dishonest": 0.0,
    "sincere": 34.0,
    "cold": 0.0,
    "warm": 34.0,
    "threatening": 0.0,
    "benevolent": 33.0,
    "repellent": 0.0,
    "likable": 34.0,
    "egoistic": 0.0,
    "altruistic": 21.0,
    "irrational": 0.0,
    "rational": 11.0
  },
  "Puerto Ricans": {
    "powerless": 999,
    "powerful": 999,
    "low status": 999,
    "high status": 999,
    "dominated": 999,
    "dominant": 999,
    "poor": 999,
    "wealthy": 999,
    "unconfident": 999,
    "confident": 999,
    "unassertive": 999,
    "competitive": 999,
    "traditional": 999,
    "modern": 999,
    "religious": 999,
    "non religious": 999,
    "conservative": 999,
    "liberal": 999,
    "untrustworthy": 999,
    "trustworthy": 999,
    "dishonest": 999,
    "sincere": 999,
    "cold": 999,
    "warm": 999,
    "threatening": 999,
    "benevolent": 999,
    "repellent": 999,
    "likable": 999,
    "egoistic": 999,
    "altruistic": 999,
    "irrational": 999,
    "rational": 999
  },
  "Gujarati people": {
    "powerless": 0.0,
    "powerful": 10.0,
    "low status": -3.0,
    "high status": 0.0,
    "dominated": 0.0,
    "dominant": 15.0,
    "poor": -11.0,
    "wealthy": 0.0,
    "unconfident": 0.0,
    "confident": 6.0,
    "unassertive": 0.0,
    "competitive": 13.0,
    "traditional": 0.0,
    "modern": 6.0,
    "religious": -8.0,
    "non religious": 0.0,
    "conservative": 0.0,
    "liberal": 11.0,
    "untrustworthy": 0.0,
    "trustworthy": 8.0,
    "dishonest": 0.0,
    "sincere": 10.0,
    "cold": 0.0,
    "warm": 29.0,
    "threatening": 0.0,
    "benevolent": 7.0,
    "repellent": 0.0,
    "likable": 16.0,
    "egoistic": 0.0,
    "altruistic": 21.0,
    "irrational": 0.0,
    "rational": 14.0
  },
  "Brahmin people": {
    "powerless": 0.0,
    "powerful": 15.0,
    "low status": -19.0,
    "high status": 0.0,
    "dominated": -12.0,
    "dominant": 0.0,
    "poor": 0.0,
    "wealthy": 18.0,
    "unconfident": -15.0,
    "confident": 0.0,
    "unassertive": 0.0,
    "competitive": 24.0,
    "traditional": 0.0,
    "modern": 20.0,
    "religious": -11.0,
    "non religious": 0.0,
    "conservative": 0.0,
    "liberal": 13.0,
    "untrustworthy": 0.0,
    "trustworthy": 11.0,
    "dishonest": -17.0,
    "sincere": 0.0,
    "cold": 0.0,
    "warm": 23.0,
    "threatening": 0.0,
    "benevolent": 17.0,
    "repellent": 0.0,
    "likable": 24.0,
    "egoistic": 0.0,
    "altruistic": 17.0,
    "irrational": 0.0,
    "rational": 25.0
  },
  "Shudra people": {
    "powerless": 999,
    "powerful": 999,
    "low status": 999,
    "high status": 999,
    "dominated": 999,
    "dominant": 999,
    "poor": 999,
    "wealthy": 999,
    "unconfident": 999,
    "confident": 999,
    "unassertive": 999,
    "competitive": 999,
    "traditional": 999,
    "modern": 999,
    "religious": 999,
    "non religious": 999,
    "conservative": 999,
    "liberal": 999,
    "untrustworthy": 999,
    "trustworthy": 999,
    "dishonest": 999,
    "sincere": 999,
    "cold": 999,
    "warm": 999,
    "threatening": 999,
    "benevolent": 999,
    "repellent": 999,
    "likable": 999,
    "egoistic": 999,
    "altruistic": 999,
    "irrational": 999,
    "rational": 999
  }
}